{
  "__type__": "cc.Mesh",
  "_name": "",
  "_objFlags": 0,
  "_native": ".bin",
  "_struct": {
    "primitives": [
      {
        "primitiveMode": 7,
        "vertexBundelIndices": [
          0
        ],
        "indexView": {
          "offset": 4416,
          "length": 912,
          "count": 456,
          "stride": 2
        }
      }
    ],
    "vertexBundles": [
      {
        "view": {
          "offset": 0,
          "length": 4416,
          "count": 92,
          "stride": 48
        },
        "attributes": [
          {
            "name": "a_position",
            "format": 32,
            "isNormalized": false
          },
          {
            "name": "a_normal",
            "format": 32,
            "isNormalized": false
          },
          {
            "name": "a_texCoord",
            "format": 21,
            "isNormalized": false
          },
          {
            "name": "a_tangent",
            "format": 43,
            "isNormalized": false
          }
        ]
      }
    ],
    "minPosition": {
      "__type__": "cc.Vec3",
      "x": -0.007312789559364319,
      "y": -0.02733212150633335,
      "z": -0.0025000202003866434
    },
    "maxPosition": {
      "__type__": "cc.Vec3",
      "x": 0.007312789559364319,
      "y": 0.0308707095682621,
      "z": 0.0024999796878546476
    }
  },
  "_dataLength": 5328,
  "_hash": 403058344
}