[{"__type__":"cc.SpriteFrame","content":{"name":"0018","rect":{"x":0,"y":0,"width":100,"height":100},"offset":{"x":0,"y":0},"originalSize":{"width":100,"height":100},"rotated":false,"capInsets":[0,0,0,0],"texture":"0bnwEJB9tI8oF4QCcs1zoc@6c48a"}},{"__type__":"cc.AnimationClip","_name":"Tower_3_Show_Anim","sample":30,"wrapMode":2,"_duration":1.0333333333333334,"_keys":[[0.03333333333333333,0.06666666666666667,0.1,0.13333333333333333,0.16666666666666666,0.2,0.23333333333333334,0.26666666666666666,0.3,0.3333333333333333,0.36666666666666664,0.4,0.43333333333333335,0.4666666666666667,0.5,0.5333333333333333,0.5666666666666667,0.6,0.6333333333333333,0.6666666666666666,0.7,0.7333333333333333,0.7666666666666667,0.8,0.8333333333333334,0.8666666666666667,0.9,0.9333333333333333,0.9666666666666667,1]],"_curves":[{"modifiers":[{"__type__":"cc.animation.ComponentPath","component":"cc.SpriteComponent"},"spriteFrame"],"data":{"keys":0,"values":[{"__uuid__":"81eByeNMlCVLItwWd1d1+u@f9941"},{"__uuid__":"19V5sD3H9O7qcsnqgGcS/f@f9941"},{"__uuid__":"bdjGxk0DxIJakyJsGz+OwZ@f9941"},{"__uuid__":"9aKRE1ZKNNVp7Ai9kzQmxb@f9941"},{"__uuid__":"d7J6GYQxROKJ9JKJtp9v1R@f9941"},{"__uuid__":"2ci/8DTjtC8Y9rBrcFxLN3@f9941"},{"__uuid__":"98x5UlaulH3o7rocf7qKSN@f9941"},{"__uuid__":"27R7i3RVZK64zGLHwgCmXl@f9941"},{"__uuid__":"eeWGA/XelLNoezxAkliRas@f9941"},{"__uuid__":"4bXzNnd49KiboKVNhUKIRX@f9941"},{"__uuid__":"92eS8w/ahBUK+xgkNMVBjH@f9941"},{"__uuid__":"72s3jl9sJH1IGtmSr0NnjN@f9941"},{"__uuid__":"4801vbGI9BM721IpLAz7pY@f9941"},{"__uuid__":"e6hpkjpMhBpJLkl2xefcAk@f9941"},{"__uuid__":"6fnpRDzsFLwKau0lrTQdex@f9941"},{"__uuid__":"f9DWGQQ5lOd4J0NKGy14jD@f9941"},{"__uuid__":"0bnwEJB9tI8oF4QCcs1zoc@f9941"},{"__uuid__":"3fsrAGy25OiZOYOVEEsXUC@f9941"},{"__uuid__":"e9NbatKcFCcKCaD+ufQoV+@f9941"},{"__uuid__":"f0FGNI1idMi64sL7q/KFJQ@f9941"},{"__uuid__":"8a5cdhHOZNf5k8dwHVrQte@f9941"},{"__uuid__":"23enxttYNCZp+pLa/svazf@f9941"},{"__uuid__":"41Zq1JtSRMAZWLOWPbnZ1f@f9941"},{"__uuid__":"47Pd2F4FhBz4CYgeSrLNuy@f9941"},{"__uuid__":"4buS4O8sFImKxeDbdgX8Oe@f9941"},{"__uuid__":"2a1NxZsthGbZvjut/YrzLT@f9941"},{"__uuid__":"7d4oGNoqxFyYAHJcPtlDGc@f9941"},{"__uuid__":"8eHDr4bZpMzphZ1PIYwZEC@f9941"},{"__uuid__":"46dthEOU5LHb/cFkG2Xxey@f9941"},{"__uuid__":"8a3cq5UbFBZ6HWKdtYlrWU@f9941"}],"easingMethods":{}}}],"_hash":1029557487},{"__type__":"cc.SpriteFrame","content":{"name":"0027","rect":{"x":0,"y":0,"width":100,"height":100},"offset":{"x":0,"y":0},"originalSize":{"width":100,"height":100},"rotated":false,"capInsets":[0,0,0,0],"texture":"2a1NxZsthGbZvjut/YrzLT@6c48a"}},{"__type__":"cc.SpriteFrame","content":{"name":"0007","rect":{"x":0,"y":0,"width":100,"height":100},"offset":{"x":0,"y":0},"originalSize":{"width":100,"height":100},"rotated":false,"capInsets":[0,0,0,0],"texture":"2ci/8DTjtC8Y9rBrcFxLN3@6c48a"}},{"__type__":"cc.SpriteFrame","content":{"name":"0019","rect":{"x":0,"y":0,"width":100,"height":100},"offset":{"x":0,"y":0},"originalSize":{"width":100,"height":100},"rotated":false,"capInsets":[0,0,0,0],"texture":"3fsrAGy25OiZOYOVEEsXUC@6c48a"}},{"__type__":"cc.SpriteFrame","content":{"name":"0011","rect":{"x":0,"y":0,"width":100,"height":100},"offset":{"x":0,"y":0},"originalSize":{"width":100,"height":100},"rotated":false,"capInsets":[0,0,0,0],"texture":"4bXzNnd49KiboKVNhUKIRX@6c48a"}},{"__type__":"cc.SpriteFrame","content":{"name":"0026","rect":{"x":0,"y":0,"width":100,"height":100},"offset":{"x":0,"y":0},"originalSize":{"width":100,"height":100},"rotated":false,"capInsets":[0,0,0,0],"texture":"4buS4O8sFImKxeDbdgX8Oe@6c48a"}},{"__type__":"cc.SpriteFrame","content":{"name":"0016","rect":{"x":0,"y":0,"width":100,"height":100},"offset":{"x":0,"y":0},"originalSize":{"width":100,"height":100},"rotated":false,"capInsets":[0,0,0,0],"texture":"6fnpRDzsFLwKau0lrTQdex@6c48a"}},{"__type__":"cc.SpriteFrame","content":{"name":"0028","rect":{"x":0,"y":0,"width":100,"height":100},"offset":{"x":0,"y":0},"originalSize":{"width":100,"height":100},"rotated":false,"capInsets":[0,0,0,0],"texture":"7d4oGNoqxFyYAHJcPtlDGc@6c48a"}},{"__type__":"cc.SpriteFrame","content":{"name":"0001","rect":{"x":0,"y":0,"width":100,"height":100},"offset":{"x":0,"y":0},"originalSize":{"width":100,"height":100},"rotated":false,"capInsets":[0,0,0,0],"texture":"8a3cq5UbFBZ6HWKdtYlrWU@6c48a"}},{"__type__":"cc.SpriteFrame","content":{"name":"0022","rect":{"x":0,"y":0,"width":100,"height":100},"offset":{"x":0,"y":0},"originalSize":{"width":100,"height":100},"rotated":false,"capInsets":[0,0,0,0],"texture":"8a5cdhHOZNf5k8dwHVrQte@6c48a"}},{"__type__":"cc.SpriteFrame","content":{"name":"0029","rect":{"x":0,"y":0,"width":100,"height":100},"offset":{"x":0,"y":0},"originalSize":{"width":100,"height":100},"rotated":false,"capInsets":[0,0,0,0],"texture":"8eHDr4bZpMzphZ1PIYwZEC@6c48a"}},{"__type__":"cc.SpriteFrame","content":{"name":"0005","rect":{"x":0,"y":0,"width":100,"height":100},"offset":{"x":0,"y":0},"originalSize":{"width":100,"height":100},"rotated":false,"capInsets":[0,0,0,0],"texture":"9aKRE1ZKNNVp7Ai9kzQmxb@6c48a"}},{"__type__":"cc.SpriteFrame","content":{"name":"0014","rect":{"x":0,"y":0,"width":100,"height":100},"offset":{"x":0,"y":0},"originalSize":{"width":100,"height":100},"rotated":false,"capInsets":[0,0,0,0],"texture":"4801vbGI9BM721IpLAz7pY@6c48a"}},{"__type__":"cc.SpriteFrame","content":{"name":"0013","rect":{"x":0,"y":0,"width":100,"height":100},"offset":{"x":0,"y":0},"originalSize":{"width":100,"height":100},"rotated":false,"capInsets":[0,0,0,0],"texture":"72s3jl9sJH1IGtmSr0NnjN@6c48a"}},{"__type__":"cc.SpriteFrame","content":{"name":"0008","rect":{"x":0,"y":0,"width":100,"height":100},"offset":{"x":0,"y":0},"originalSize":{"width":100,"height":100},"rotated":false,"capInsets":[0,0,0,0],"texture":"98x5UlaulH3o7rocf7qKSN@6c48a"}},{"__type__":"cc.SpriteFrame","content":{"name":"0023","rect":{"x":0,"y":0,"width":100,"height":100},"offset":{"x":0,"y":0},"originalSize":{"width":100,"height":100},"rotated":false,"capInsets":[0,0,0,0],"texture":"23enxttYNCZp+pLa/svazf@6c48a"}},{"__type__":"cc.SpriteFrame","content":{"name":"0025","rect":{"x":0,"y":0,"width":100,"height":100},"offset":{"x":0,"y":0},"originalSize":{"width":100,"height":100},"rotated":false,"capInsets":[0,0,0,0],"texture":"47Pd2F4FhBz4CYgeSrLNuy@6c48a"}},{"__type__":"cc.SpriteFrame","content":{"name":"0009","rect":{"x":0,"y":0,"width":100,"height":100},"offset":{"x":0,"y":0},"originalSize":{"width":100,"height":100},"rotated":false,"capInsets":[0,0,0,0],"texture":"27R7i3RVZK64zGLHwgCmXl@6c48a"}},{"__type__":"cc.SpriteFrame","content":{"name":"0024","rect":{"x":0,"y":0,"width":100,"height":100},"offset":{"x":0,"y":0},"originalSize":{"width":100,"height":100},"rotated":false,"capInsets":[0,0,0,0],"texture":"41Zq1JtSRMAZWLOWPbnZ1f@6c48a"}},{"__type__":"cc.SpriteFrame","content":{"name":"0030","rect":{"x":0,"y":0,"width":100,"height":100},"offset":{"x":0,"y":0},"originalSize":{"width":100,"height":100},"rotated":false,"capInsets":[0,0,0,0],"texture":"46dthEOU5LHb/cFkG2Xxey@6c48a"}},{"__type__":"cc.SpriteFrame","content":{"name":"0003","rect":{"x":0,"y":0,"width":100,"height":100},"offset":{"x":0,"y":0},"originalSize":{"width":100,"height":100},"rotated":false,"capInsets":[0,0,0,0],"texture":"19V5sD3H9O7qcsnqgGcS/f@6c48a"}},{"__type__":"cc.SpriteFrame","content":{"name":"0002","rect":{"x":0,"y":0,"width":100,"height":100},"offset":{"x":0,"y":0},"originalSize":{"width":100,"height":100},"rotated":false,"capInsets":[0,0,0,0],"texture":"81eByeNMlCVLItwWd1d1+u@6c48a"}},{"__type__":"cc.SpriteFrame","content":{"name":"0012","rect":{"x":0,"y":0,"width":100,"height":100},"offset":{"x":0,"y":0},"originalSize":{"width":100,"height":100},"rotated":false,"capInsets":[0,0,0,0],"texture":"92eS8w/ahBUK+xgkNMVBjH@6c48a"}},[{"__type__":"cc.Prefab","data":{"__id__":1}},{"__type__":"cc.Node","_name":"Tower_3_Show_Anim","_components":[{"__type__":"cc.UITransformComponent","node":{"__id__":1}},{"__type__":"cc.SpriteComponent","node":{"__id__":1},"_spriteFrame":{"__uuid__":"57UgcWSMhKGYrPQcn4d3+w@f9941"},"_sizeMode":0},{"__type__":"cc.AnimationComponent","_name":"Tower_1_Show_Anim<AnimationComponent>","node":{"__id__":1},"playOnLoad":true,"_clips":[{"__uuid__":"1eYjQHyaRPFrnt41/L1zXH"}],"_defaultClip":{"__uuid__":"1eYjQHyaRPFrnt41/L1zXH"}}],"_prefab":{"__type__":"cc.PrefabInfo","root":{"__id__":1},"asset":{"__id__":0},"fileId":"6c9YNmuz9PKJEc02Z8Opvf","_synced":{"default":false,"serializable":false}},"_lscale":{"__type__":"cc.Vec3","x":1.5,"y":1.5,"z":1.5},"_layer":33554432}],{"__type__":"cc.SpriteFrame","content":{"name":"0004","rect":{"x":0,"y":0,"width":100,"height":100},"offset":{"x":0,"y":0},"originalSize":{"width":100,"height":100},"rotated":false,"capInsets":[0,0,0,0],"texture":"bdjGxk0DxIJakyJsGz+OwZ@6c48a"}},{"__type__":"cc.SpriteFrame","content":{"name":"0006","rect":{"x":0,"y":0,"width":100,"height":100},"offset":{"x":0,"y":0},"originalSize":{"width":100,"height":100},"rotated":false,"capInsets":[0,0,0,0],"texture":"d7J6GYQxROKJ9JKJtp9v1R@6c48a"}},{"__type__":"cc.SpriteFrame","content":{"name":"0020","rect":{"x":0,"y":0,"width":100,"height":100},"offset":{"x":0,"y":0},"originalSize":{"width":100,"height":100},"rotated":false,"capInsets":[0,0,0,0],"texture":"e9NbatKcFCcKCaD+ufQoV+@6c48a"}},{"__type__":"cc.SpriteFrame","content":{"name":"0015","rect":{"x":0,"y":0,"width":100,"height":100},"offset":{"x":0,"y":0},"originalSize":{"width":100,"height":100},"rotated":false,"capInsets":[0,0,0,0],"texture":"e6hpkjpMhBpJLkl2xefcAk@6c48a"}},{"__type__":"cc.SpriteFrame","content":{"name":"0010","rect":{"x":0,"y":0,"width":100,"height":100},"offset":{"x":0,"y":0},"originalSize":{"width":100,"height":100},"rotated":false,"capInsets":[0,0,0,0],"texture":"eeWGA/XelLNoezxAkliRas@6c48a"}},{"__type__":"cc.SpriteFrame","content":{"name":"0017","rect":{"x":0,"y":0,"width":100,"height":100},"offset":{"x":0,"y":0},"originalSize":{"width":100,"height":100},"rotated":false,"capInsets":[0,0,0,0],"texture":"f9DWGQQ5lOd4J0NKGy14jD@6c48a"}},{"__type__":"cc.SpriteFrame","content":{"name":"0021","rect":{"x":0,"y":0,"width":100,"height":100},"offset":{"x":0,"y":0},"originalSize":{"width":100,"height":100},"rotated":false,"capInsets":[0,0,0,0],"texture":"f0FGNI1idMi64sL7q/KFJQ@6c48a"}}]
