[[{"__type__":"cc.Prefab","data":{"__id__":1}},{"__type__":"cc.Node","_name":"狂暴道具","_children":[{"__id__":2}],"_components":[{"__type__":"cc.UITransformComponent","node":{"__id__":1}},{"__type__":"cc.SpriteComponent","node":{"__id__":1},"_type":1,"_sizeMode":0},{"__type__":"137d7fAtX1CO423/GncRui3","node":{"__id__":1},"objectType":"狂暴道具","rootNode":{"__id__":2}}],"_prefab":{"__type__":"cc.PrefabInfo","root":{"__id__":1},"asset":{"__id__":0},"fileId":"08x190D+pED7vHSYa/aogb","_synced":{"default":false,"serializable":false}},"_layer":33554432},{"__type__":"cc.Node","_name":"狂暴道具","_parent":{"__id__":1},"_components":[{"__type__":"cc.UITransformComponent","node":{"__id__":2},"_contentSize":{"__type__":"cc.Size","width":84,"height":82}},{"__type__":"cc.SpriteComponent","node":{"__id__":2},"_spriteFrame":{"__uuid__":"32DMDFwvJF564brij1z1fC@f9941"}}],"_prefab":{"__type__":"cc.PrefabInfo","root":{"__id__":1},"asset":{"__id__":0},"fileId":"04cnW2C1lB1bGvOGYd/0Bv","_synced":{"default":false,"serializable":false}},"_layer":33554432}],{"__type__":"cc.SpriteFrame","content":{"name":"狂暴道具_红","rect":{"x":0,"y":0,"width":84,"height":82},"offset":{"x":0,"y":0},"originalSize":{"width":84,"height":82},"rotated":false,"capInsets":[0,0,0,0],"texture":"32DMDFwvJF564brij1z1fC@6c48a"}}]
